[
  {
    "id": 0,
    "title": "Офисные помещения",
    "count": "800+ объектов",
    "description": "Современные офисные пространства в бизнес-центрах и отдельно стоящих зданиях. Отделка под ключ, перепланировка, инженерные системы. Подходят для штаб-квартир, коворкингов и представительств. Все объекты с документами и готовы к использованию.",
    "images": [
      "https://images.unsplash.com/photo-1762758731234-2569e31afa02?crop=entropy&cs=tinysrgb&fit=max&fm=jpg&q=80&w=1080",
      "https://images.unsplash.com/photo-1497366216548-37526070297c?w=800&q=80",
      "https://images.unsplash.com/photo-1524758631624-e2822e304c36?w=800&q=80"
    ],
    "icon": "🏢"
  },
  {
    "id": 1,
    "title": "Складские помещения",
    "count": "500+ объектов",
    "description": "Складские комплексы и логистические центры с удобными подъездами, погрузочными площадками и офисными блоками. Высота потолков от 4 до 12 м, возможность разделения на зоны. Идеально для производства, хранения и дистрибуции.",
    "images": [
      "https://images.unsplash.com/photo-1621384843923-f1a2d8b7eb3e?crop=entropy&cs=tinysrgb&fit=max&fm=jpg&q=80&w=1080",
      "https://images.unsplash.com/photo-1586528116311-ad8dd3c8310d?w=800&q=80",
      "https://images.unsplash.com/photo-1504307651254-35680f356dfd?w=800&q=80"
    ],
    "icon": "📦"
  },
  {
    "id": 2,
    "title": "Земельные участки",
    "count": "300+ объектов",
    "description": "Земельные участки под коммерческую застройку, склады и производство. Участки с подведёнными коммуникациями и разрешённым использованием. Подбор по локации, площади и назначению для развития вашего бизнеса.",
    "images": [
      "https://images.unsplash.com/photo-1764222233275-87dc016c11dc?crop=entropy&cs=tinysrgb&fit=max&fm=jpg&q=80&w=1080",
      "https://images.unsplash.com/photo-1500387467466-73060c3e4b63?w=800&q=80",
      "https://images.unsplash.com/photo-1477959858617-67f85cf4f1df?w=800&q=80"
    ],
    "icon": "📍"
  }
]
